mycalc/calculator.py
nachunjae-0.0.post1.dist-info/METADATA
nachunjae-0.0.post1.dist-info/WHEEL
nachunjae-0.0.post1.dist-info/top_level.txt
nachunjae-0.0.post1.dist-info/RECORD
