Metadata-Version: 2.1
Name: nachunjae
Version: 0.0.post1
Summary: oss-dev my calculator 0001
Home-page: https://github.com/Jo-subin/calc
Download-URL: https://github.com/Jo-subin/calc/archive/refs/tags/v0.0.1.zip
Author: subinjo
License: UNKNOWN
Platform: UNKNOWN
Classifier: Programming Language :: Python :: 3
